odoo/addons/pos_ticket_without_price/README.rst
odoo/addons/pos_ticket_without_price/__init__.py
odoo/addons/pos_ticket_without_price/__manifest__.py
odoo/addons/pos_ticket_without_price/i18n/ca.po
odoo/addons/pos_ticket_without_price/i18n/ca_ES.po
odoo/addons/pos_ticket_without_price/i18n/es.po
odoo/addons/pos_ticket_without_price/i18n/pos_ticket_without_price.pot
odoo/addons/pos_ticket_without_price/readme/CONTRIBUTORS.rst
odoo/addons/pos_ticket_without_price/readme/DESCRIPTION.rst
odoo/addons/pos_ticket_without_price/readme/ROADMAP.rst
odoo/addons/pos_ticket_without_price/readme/USAGE.rst
odoo/addons/pos_ticket_without_price/static/description/icon.png
odoo/addons/pos_ticket_without_price/static/description/index.html
odoo/addons/pos_ticket_without_price/static/src/js/screens.js
odoo/addons/pos_ticket_without_price/static/src/xml/pos.xml
odoo/addons/pos_ticket_without_price/views/pos_templates.xml
odoo12_addon_pos_ticket_without_price-12.0.1.0.1.dist-info/METADATA
odoo12_addon_pos_ticket_without_price-12.0.1.0.1.dist-info/WHEEL
odoo12_addon_pos_ticket_without_price-12.0.1.0.1.dist-info/top_level.txt
odoo12_addon_pos_ticket_without_price-12.0.1.0.1.dist-info/RECORD
